trytoncommunity_web_shop_woocommerce-7.0.4.dist-info/licenses/LICENSE
trytond/modules/web_shop_woocommerce/__init__.py
trytond/modules/web_shop_woocommerce/exceptions.py
trytond/modules/web_shop_woocommerce/ir.py
trytond/modules/web_shop_woocommerce/message.xml
trytond/modules/web_shop_woocommerce/party.py
trytond/modules/web_shop_woocommerce/product.py
trytond/modules/web_shop_woocommerce/product.xml
trytond/modules/web_shop_woocommerce/tryton.cfg
trytond/modules/web_shop_woocommerce/web.py
trytond/modules/web_shop_woocommerce/web.xml
trytond/modules/web_shop_woocommerce/locale/ca.po
trytond/modules/web_shop_woocommerce/locale/es.po
trytond/modules/web_shop_woocommerce/tests/__init__.py
trytond/modules/web_shop_woocommerce/tests/test_module.py
trytond/modules/web_shop_woocommerce/view/category_form.xml
trytond/modules/web_shop_woocommerce/view/shop_form.xml
trytoncommunity_web_shop_woocommerce-7.0.4.dist-info/METADATA
trytoncommunity_web_shop_woocommerce-7.0.4.dist-info/WHEEL
trytoncommunity_web_shop_woocommerce-7.0.4.dist-info/entry_points.txt
trytoncommunity_web_shop_woocommerce-7.0.4.dist-info/top_level.txt
trytoncommunity_web_shop_woocommerce-7.0.4.dist-info/RECORD
